orbit_predictor/__init__.py
orbit_predictor/angles.py
orbit_predictor/constants.py
orbit_predictor/coordinate_systems.py
orbit_predictor/exceptions.py
orbit_predictor/groundtrack.py
orbit_predictor/keplerian.py
orbit_predictor/locations.py
orbit_predictor/sources.py
orbit_predictor/utils.py
orbit_predictor/version.py
orbit_predictor/predictors/__init__.py
orbit_predictor/predictors/_minimize.py
orbit_predictor/predictors/accurate.py
orbit_predictor/predictors/base.py
orbit_predictor/predictors/keplerian.py
orbit_predictor/predictors/numerical.py
orbit_predictor/predictors/pass_iterators.py
orbit_predictor/predictors/tle.py
orbit_predictor-1.15.2.dist-info/licenses/LICENSE
orbit_predictor-1.15.2.dist-info/METADATA
orbit_predictor-1.15.2.dist-info/WHEEL
orbit_predictor-1.15.2.dist-info/top_level.txt
orbit_predictor-1.15.2.dist-info/RECORD
