Metadata-Version: 2.4
Name: orbit-predictor
Version: 1.15.2
Summary: Python library to propagate satellite orbits.
Home-page: https://github.com/satellogic/orbit-predictor
Author: Satellogic SA
Author-email: oss@satellogic.com
License: MIT
Keywords: orbit,sgp4,TLE,space,satellites
Classifier: Development Status :: 5 - Production/Stable
Classifier: Environment :: Console
Classifier: Intended Audience :: Science/Research
Classifier: Operating System :: OS Independent
Classifier: Programming Language :: Python
Classifier: Topic :: Software Development :: Libraries :: Python Modules
Classifier: Topic :: Utilities
Classifier: Programming Language :: Python :: 3
Requires-Python: >=3.4
License-File: LICENSE
Requires-Dist: numpy>=1.8.2
Requires-Dist: sgp4>=2.5
Requires-Dist: requests
Provides-Extra: fast
Requires-Dist: numba>=0.38; extra == "fast"
Requires-Dist: scipy>=0.16; extra == "fast"
Provides-Extra: dev
Requires-Dist: hypothesis<5.0.0; extra == "dev"
Requires-Dist: flake8; extra == "dev"
Requires-Dist: hypothesis; extra == "dev"
Requires-Dist: mock; extra == "dev"
Requires-Dist: logassert; extra == "dev"
Requires-Dist: pytest; extra == "dev"
Requires-Dist: pytest-coverage; extra == "dev"
Requires-Dist: pytest-benchmark; extra == "dev"
Requires-Dist: pytz; extra == "dev"
Requires-Dist: setuptools; extra == "dev"
Dynamic: author
Dynamic: author-email
Dynamic: classifier
Dynamic: description
Dynamic: home-page
Dynamic: keywords
Dynamic: license
Dynamic: license-file
Dynamic: provides-extra
Dynamic: requires-dist
Dynamic: requires-python
Dynamic: summary
